{"queue":[{"name":"messaging_events","userId":"92306386","value":{"event_level":4,"ratio_charts_enabled":true,"alert_enabled":true,"loopback_enabled":true},"segment":{"segmentId":8722258},"configHash":"ee8a32e4d4105464d11a01e72a4dc580","startTimestamp":1672394400.0,"endTimestamp":0.0,"queueHash":"cc334d266912b98874606fd61741a144"},{"name":"messaging_events","userId":"92306386","value":{"event_level":4,"ratio_charts_enabled":true,"alert_enabled":true,"loopback_enabled":false},"segment":{"segmentId":0},"configHash":"1a4de79bae52ce111683b261ab10d2dc","startTimestamp":0.0,"endTimestamp":0.0,"queueHash":"cc334d266912b98874606fd61741a144"}]}